sccpy/1.py
sccpy/2.py
sccpy/3.py
sccpy/4.py
sccpy/5.py
sccpy/6.py
sccpy/7.py
sccpy/8.py
sccpy/main.py
sccpy/tkn.py
sccpy-0.1.1.dist-info/METADATA
sccpy-0.1.1.dist-info/WHEEL
sccpy-0.1.1.dist-info/top_level.txt
sccpy-0.1.1.dist-info/RECORD
