Metadata-Version: 2.4
Name: sccpy
Version: 0.1.1
Summary: Add your description here
Requires-Python: >=3.10
Requires-Dist: numpy>=2.2.6
Requires-Dist: pandas>=2.3.3
Requires-Dist: scikit-learn>=1.7.2
Requires-Dist: scipy>=1.15.3
